simple_bdd/__init__.py
simple_bdd/bdd.py
simple_bdd/bddContext.py
simple_bdd-0.2.0.dist-info/LICENSE
simple_bdd-0.2.0.dist-info/METADATA
simple_bdd-0.2.0.dist-info/WHEEL
simple_bdd-0.2.0.dist-info/RECORD
