Metadata-Version: 2.1
Name: simple-bdd
Version: 0.2.0
Summary: A simple BDD library for testing python code.
Home-page: https://github.com/redhotbadger/simple-bdd
Author: RedHotBadger
Requires-Python: >=3.10,<4.0
Classifier: Programming Language :: Python :: 3
Classifier: Programming Language :: Python :: 3.10
Classifier: Programming Language :: Python :: 3.11
Classifier: Programming Language :: Python :: 3.12
Requires-Dist: pytest (>=8.2.2,<9.0.0) ; python_version == "3.10"
Requires-Dist: pytest (>=8.2.2,<9.0.0) ; python_version >= "3.11" and python_version < "4.0"
